README.md
setup.py
lbrlabs_pulumi_scaleway/__init__.py
lbrlabs_pulumi_scaleway/_inputs.py
lbrlabs_pulumi_scaleway/_utilities.py
lbrlabs_pulumi_scaleway/account_project.py
lbrlabs_pulumi_scaleway/account_ssh_key.py
lbrlabs_pulumi_scaleway/apple_slicon_valley_server.py
lbrlabs_pulumi_scaleway/baremetal_server.py
lbrlabs_pulumi_scaleway/cockpit.py
lbrlabs_pulumi_scaleway/cockpit_grafana_user.py
lbrlabs_pulumi_scaleway/cockpit_token.py
lbrlabs_pulumi_scaleway/container.py
lbrlabs_pulumi_scaleway/container_cron.py
lbrlabs_pulumi_scaleway/container_domain.py
lbrlabs_pulumi_scaleway/container_namespace.py
lbrlabs_pulumi_scaleway/container_token.py
lbrlabs_pulumi_scaleway/container_trigger.py
lbrlabs_pulumi_scaleway/database.py
lbrlabs_pulumi_scaleway/database_acl.py
lbrlabs_pulumi_scaleway/database_backup.py
lbrlabs_pulumi_scaleway/database_instance.py
lbrlabs_pulumi_scaleway/database_privilege.py
lbrlabs_pulumi_scaleway/database_read_replica.py
lbrlabs_pulumi_scaleway/database_user.py
lbrlabs_pulumi_scaleway/documentdb_database.py
lbrlabs_pulumi_scaleway/documentdb_instance.py
lbrlabs_pulumi_scaleway/documentdb_private_network_endpoint.py
lbrlabs_pulumi_scaleway/documentdb_privilege.py
lbrlabs_pulumi_scaleway/documentdb_read_replica.py
lbrlabs_pulumi_scaleway/documentdb_user.py
lbrlabs_pulumi_scaleway/domain_record.py
lbrlabs_pulumi_scaleway/domain_zone.py
lbrlabs_pulumi_scaleway/flexible_ip.py
lbrlabs_pulumi_scaleway/flexible_ip_mac_address.py
lbrlabs_pulumi_scaleway/function.py
lbrlabs_pulumi_scaleway/function_cron.py
lbrlabs_pulumi_scaleway/function_domain.py
lbrlabs_pulumi_scaleway/function_namespace.py
lbrlabs_pulumi_scaleway/function_token.py
lbrlabs_pulumi_scaleway/function_trigger.py
lbrlabs_pulumi_scaleway/get_account_project.py
lbrlabs_pulumi_scaleway/get_account_ssh_key.py
lbrlabs_pulumi_scaleway/get_availability_zones.py
lbrlabs_pulumi_scaleway/get_baremetal_offer.py
lbrlabs_pulumi_scaleway/get_baremetal_option.py
lbrlabs_pulumi_scaleway/get_baremetal_os.py
lbrlabs_pulumi_scaleway.egg-info/PKG-INFO
lbrlabs_pulumi_scaleway.egg-info/SOURCES.txt
lbrlabs_pulumi_scaleway.egg-info/dependency_links.txt
lbrlabs_pulumi_scaleway.egg-info/not-zip-safe
lbrlabs_pulumi_scaleway.egg-info/requires.txt
lbrlabs_pulumi_scaleway.egg-info/top_level.txt
