Metadata-Version: 2.1
Name: lbrlabs-pulumi-scaleway
Version: 1.11.0
Summary: A Pulumi package for creating and managing scaleway cloud resources.
Home-page: https://leebriggs.co.uk/projects#pulumi-scaleway
License: Apache-2.0
Project-URL: Repository, https://github.com/lbrlabs/pulumi-scaleway
Keywords: pulumi scaleway lbrlabs
Platform: UNKNOWN
Requires-Python: >=3.7
